{
  "id": "cards",
  "type": "SharedSlice",
  "name": "Cards",
  "description": "Cards",
  "variations": [
    {
      "id": "default",
      "name": "Default",
      "docURL": "...",
      "version": "sktwi1xtmkfgx8626",
      "description": "Cards",
      "primary": {
        "size": {
          "type": "Select",
          "config": {
            "label": "Размер карточек",
            "placeholder": "",
            "options": ["m", "s", "l"]
          }
        }
      },
      "items": {
        "title": {
          "type": "Text",
          "config": { "label": "title", "placeholder": "" }
        },
        "description": {
          "type": "Text",
          "config": { "label": "description", "placeholder": "" }
        },
        "image": {
          "type": "Image",
          "config": { "label": "image", "constraint": {}, "thumbnails": [] }
        },
        "link": {
          "type": "Text",
          "config": { "label": "link", "placeholder": "" }
        }
      },
      "imageUrl": "https://images.prismic.io/vagmen1/shared-slices/cards/default/80f5e491acf7df5e0a44d35faa65f4908b52ccaa.png?auto=compress%2Cformat"
    }
  ]
}
